prodrisk_shop_simulator/__init__.py
prodrisk_shop_simulator/cuts.py
prodrisk_shop_simulator/input/input_consistency_check.py
prodrisk_shop_simulator/input/pump.py
prodrisk_shop_simulator/input/read_prodrisk_data_from_LTM_folder.py
prodrisk_shop_simulator/process_results.py
prodrisk_shop_simulator/results/README.md
prodrisk_shop_simulator/services/shop_derived_attributes.py
prodrisk_shop_simulator/simulator.py
prodrisk_shop_simulator-1.1.2.dist-info/METADATA
prodrisk_shop_simulator-1.1.2.dist-info/WHEEL
prodrisk_shop_simulator-1.1.2.dist-info/RECORD
