Metadata-Version: 2.4
Name: prodrisk-shop-simulator
Version: 1.1.2
Summary: Package for simulating hydro power systems with Prodrisk first followed by SHOP using cuts from Prodrisk.
Requires-Python: >=3.10,<4.0
Classifier: Programming Language :: Python :: 3
Classifier: Programming Language :: Python :: 3.10
Classifier: Programming Language :: Python :: 3.11
Classifier: Programming Language :: Python :: 3.12
Classifier: Programming Language :: Python :: 3.13
Classifier: Programming Language :: Python :: 3.14
Requires-Dist: PyYAML (>=6.0,<7.0)
Requires-Dist: h5py (>=3.8.0,<4.0.0)
Requires-Dist: numpy (>=1.24.2,<2.0.0)
Requires-Dist: pandas (>=2.0.0,<3.0.0)
Requires-Dist: pyprodrisk (>=1.3.0,<2.0.0)
Requires-Dist: scipy (>=1.11.4,<2.0.0)
Requires-Dist: sintef-pyshop (>=1.4.9,<2.0.0)
Requires-Dist: tables (>=3.8.0,<4.0.0)
Requires-Dist: tqdm (>=4.65.0,<5.0.0)
